cli/Pyocs_cli.py
cli/__init__.py
customers/__init__.py
customers/dtruler.py
customers/customer_chaoye/__init__.py
customers/customer_chaoye/chaoye_ruler.py
customers/customer_chaoye/parse_excel.py
customers/customer_chaoye/HV553/__init__.py
customers/customer_chaoye/HV553/ruler.py
customers/customer_chaoye/MS358/__init__.py
customers/customer_chaoye/MS358/ruler.py
customers/customer_chaoye/MT5510/__init__.py
customers/customer_chaoye/MT5510/ruler.py
customers/customer_chaoye/RDA8503/__init__.py
customers/customer_chaoye/RDA8503/ruler.py
customers/customer_chaoye/V56/__init__.py
customers/customer_chaoye/V56/ruler.py
customers/customer_chaoye/comment_sw_needs_to_ocs/DailySwToOscEmailReport.py
customers/customer_chaoye/comment_sw_needs_to_ocs/__init__.py
customers/customer_chaoye/comment_sw_needs_to_ocs/cy_demand_to_ocs.py
customers/customer_chaoye/comment_sw_needs_to_ocs/cyocs_all_excel.py
customers/customer_chaoye/comment_sw_needs_to_ocs/excel_deal.py
customers/customer_chaoye/confirm_software/__init__.py
customers/customer_chaoye/confirm_software/chaoye_confirm_software.py
customers/customer_common/common_database.py
customers/customer_common/cvte_send_msg.py
customers/customer_common/ConfirmSwEmail/CustomerConfirmSwEmail.py
customers/customer_common/ConfirmSwEmail/DailyConfrimSwEmailReport.py
customers/customer_common/special_order_warning/special_order_warning.py
customers/customer_dg/__init__.py
customers/customer_dg/cfgManager.py
customers/customer_dg/dg_cus_order.py
customers/customer_dg/dg_database.py
customers/customer_dg/dg_rename_xml.py
customers/customer_dg/dg_reuse_sw.py
customers/customer_dg/dg_sw_task_msg.py
customers/customer_dg/excelManager.py
customers/customer_dg/res/rule.xml
customers/customer_hanke/__init__.py
customers/customer_hanke/atuo_do_daice_sw/My_pyocs_fun.py
customers/customer_hanke/atuo_do_daice_sw/__init__.py
customers/customer_hanke/atuo_do_daice_sw/atuo_do_daice_sw--V0.2.zip
pyocs-4.4.7.dist-info/LICENSE
pyocs-4.4.7.dist-info/METADATA
pyocs-4.4.7.dist-info/WHEEL
pyocs-4.4.7.dist-info/entry_points.txt
pyocs-4.4.7.dist-info/top_level.txt
pyocs-4.4.7.dist-info/RECORD
