Metadata-Version: 2.1
Name: pyocs
Version: 4.4.7
Summary: Python ocs 自动化程序
Home-page: https://gitlab.gz.cvte.cn/python-tool/pyocs
Author: zhubowen3432
Author-email: zhubowen3432@cvte.com
License: MIT
Platform: UNKNOWN
Classifier: License :: OSI Approved :: MIT License
Classifier: Programming Language :: Python
Classifier: Programming Language :: Python :: 3
Classifier: Programming Language :: Python :: 3.4
Classifier: Programming Language :: Python :: Implementation :: CPython
Classifier: Programming Language :: Python :: Implementation :: PyPy
Requires-Python: >=3.4.0
Requires-Dist: requests (>=2.21.0)
Requires-Dist: click (>=7.0)
Requires-Dist: lxml (~=4.6.2)
Requires-Dist: python-jenkins (>=1.4.0)
Requires-Dist: GitPython
Requires-Dist: requests-toolbelt
Requires-Dist: BeautifulSoup4
Requires-Dist: openpyxl (>=2.5.14)
Requires-Dist: xlrd
Requires-Dist: portalocker
Requires-Dist: colorama (==0.2.5)
Requires-Dist: jira
Requires-Dist: pandas
Requires-Dist: pyDes
Requires-Dist: pymysql
Requires-Dist: apollo-client (==0.9.1)
Requires-Dist: pycrypto (==2.6.1)
Requires-Dist: pycryptodome (==3.10.1)
Requires-Dist: tqdm (==4.59.0)
Requires-Dist: pynacl (==1.0.1)
Requires-Dist: cryptography (==3.3.2)
Requires-Dist: bcrypt (==3.1.3)
Requires-Dist: paramiko (==2.7.1)
Provides-Extra: fancy_feature
Requires-Dist: PySimpleGUI ; extra == 'fancy_feature'
